scH5Loader/__init__.py
scH5Loader/datasets.py
scH5Loader/exploration.py
scH5Loader/loading.py
scH5Loader/py.typed
scH5Loader-0.1.1.dist-info/LICENSE
scH5Loader-0.1.1.dist-info/METADATA
scH5Loader-0.1.1.dist-info/WHEEL
scH5Loader-0.1.1.dist-info/top_level.txt
scH5Loader-0.1.1.dist-info/RECORD
