Metadata-Version: 2.1
Name: scH5Loader
Version: 0.1.1
Summary: investigate h5ad contents and load in subset of the original data
Author: Antony Rose
Author-email: antonyrose17@gmail.ac.uk
License: MIT
Requires-Python: >=3.6
License-File: LICENSE
Requires-Dist: numpy
Requires-Dist: pandas
Requires-Dist: anndata
Requires-Dist: h5py
Requires-Dist: scipy
Requires-Dist: tqdm
Requires-Dist: numba
Provides-Extra: testing
Requires-Dist: pytest>=6.0; extra == "testing"
Requires-Dist: pytest-cov>=2.0; extra == "testing"
Requires-Dist: mypy>=0.910; extra == "testing"
Requires-Dist: flake8>=3.9; extra == "testing"
Requires-Dist: tox>=3.24; extra == "testing"
